binance_sdk_staking/__init__.py
binance_sdk_staking/metadata.py
binance_sdk_staking/rest_api/__init__.py
binance_sdk_staking/rest_api/api/__init__.py
binance_sdk_staking/rest_api/api/eth_staking_api.py
binance_sdk_staking/rest_api/api/on_chain_yields_api.py
binance_sdk_staking/rest_api/api/soft_staking_api.py
binance_sdk_staking/rest_api/api/sol_staking_api.py
binance_sdk_staking/rest_api/models/__init__.py
binance_sdk_staking/rest_api/models/claim_boost_rewards_response.py
binance_sdk_staking/rest_api/models/enums.py
binance_sdk_staking/rest_api/models/eth_staking_account_response.py
binance_sdk_staking/rest_api/models/eth_staking_account_response_holdings.py
binance_sdk_staking/rest_api/models/eth_staking_account_response_profit.py
binance_sdk_staking/rest_api/models/get_bnsol_rate_history_response.py
binance_sdk_staking/rest_api/models/get_bnsol_rate_history_response_rows_inner.py
binance_sdk_staking/rest_api/models/get_bnsol_rate_history_response_rows_inner_boost_rewards_inner.py
binance_sdk_staking/rest_api/models/get_bnsol_rewards_history_response.py
binance_sdk_staking/rest_api/models/get_bnsol_rewards_history_response_rows_inner.py
binance_sdk_staking/rest_api/models/get_boost_rewards_history_response.py
binance_sdk_staking/rest_api/models/get_boost_rewards_history_response_rows_inner.py
binance_sdk_staking/rest_api/models/get_current_eth_staking_quota_response.py
binance_sdk_staking/rest_api/models/get_eth_redemption_history_response.py
binance_sdk_staking/rest_api/models/get_eth_redemption_history_response_rows_inner.py
binance_sdk_staking/rest_api/models/get_eth_staking_history_response.py
binance_sdk_staking/rest_api/models/get_eth_staking_history_response_rows_inner.py
binance_sdk_staking/rest_api/models/get_on_chain_yields_locked_personal_left_quota_response.py
binance_sdk_staking/rest_api/models/get_on_chain_yields_locked_product_list_response.py
binance_sdk_staking/rest_api/models/get_on_chain_yields_locked_product_list_response_rows_inner.py
binance_sdk_staking-5.2.0.dist-info/METADATA
binance_sdk_staking-5.2.0.dist-info/WHEEL
binance_sdk_staking-5.2.0.dist-info/licenses/LICENCE
binance_sdk_staking-5.2.0.dist-info/RECORD
